rdcrm/__init__.py
rdcrm/customer.py
rdcrm/login.py
rdcrm/product.py
rdcrm/salesOrder.py
rdcrm/bill/__init__.py
rdcrm/bill/receiveReturn.py
rdcrm/bill/salesInvoice.py
rdcrm/bill/salesOrder.py
rdcrm/bill/salesOutStock.py
rdcrm/bill/salesReturn.py
rdcrm/bill/salesStatement.py
rdcrm/bill/sampleOutStock.py
rdcrm/md/__init__.py
rdcrm/md/customer.py
rdcrm/md/product.py
rdcrm-1.1.0.dist-info/LICENSE
rdcrm-1.1.0.dist-info/METADATA
rdcrm-1.1.0.dist-info/WHEEL
rdcrm-1.1.0.dist-info/top_level.txt
rdcrm-1.1.0.dist-info/RECORD
