Metadata-Version: 2.1
Name: rdcrm
Version: 1.1.0
Summary: crm web api in py language 
Home-page: http://www.reshapedata.com
Author: hulilei
Author-email: hulilei@takewiki.com.cn
License: Apache License
Keywords: reshapedata,cdcrm
Platform: UNKNOWN
Requires-Python: >=3.6
License-File: LICENSE
Requires-Dist: requests
